Week4/lab8/fibonacci_generator.v
module fibonacci_generator (
    input clk,        // Clock signal
    input rst,        // Synchronous reset
    input enable,     // Enable signal for calculating next Fibonacci number
    output reg [63:0] fib_out  // Output for the current Fibonacci number
);

reg [63:0] fib_prev1;  // F(n-1)
reg [63:0] fib_prev2;  // F(n-2)


always @(posedge clk or posedge rst) begin
    if (rst) begin
        // Initialize Fibonacci numbers
        fib_prev1 <= 64'd1;  // F(1) = 1
        fib_prev2 <= 64'd0;  // F(0) = 0
        fib_out <= 64'd0;    // Current Fibonacci number = F(0)
    end else if (enable) begin
        // Update previous Fibonacci numbers
        fib_prev2 <= fib_prev1;
        fib_prev1 <= fib_prev1 + fib_prev2;
	fib_out <= fib_prev1;
    end
end

endmodule

Week4/lab8/fibonacci.vcd
$version Generated by VerilatedVcd $end
$timescale 1ps $end
 $scope module TOP $end
  $var wire 1 # clk $end
  $var wire 1 $ rst $end
  $var wire 1 % enable $end
  $var wire 64 & fib_out [63:0] $end
  $scope module fibonacci_generator $end
   $var wire 1 # clk $end
   $var wire 1 $ rst $end
   $var wire 1 % enable $end
   $var wire 64 & fib_out [63:0] $end
   $var wire 64 ( fib_prev1 [63:0] $end
   $var wire 64 * fib_prev2 [63:0] $end
  $upscope $end
 $upscope $end
$enddefinitions $end


#0
0#
0$
0%
b0000000000000000000000000000000000000000000000000000000000000000 &
b0000000000000000000000000000000000000000000000000000000000000000 (
b0000000000000000000000000000000000000000000000000000000000000000 *
#1
1$
1%
#2
1#
b0000000000000000000000000000000000000000000000000000000000000001 (
#3
0#
#4
1#
#5
0#
#6
1#
#7
0#
#8
1#
#9
0#
#10
1#
0$
b0000000000000000000000000000000000000000000000000000000000000001 &
b0000000000000000000000000000000000000000000000000000000000000001 *
#11
0#
#12
1#
b0000000000000000000000000000000000000000000000000000000000000010 (
#13
0#
#14
1#
b0000000000000000000000000000000000000000000000000000000000000010 &
b0000000000000000000000000000000000000000000000000000000000000011 (
b0000000000000000000000000000000000000000000000000000000000000010 *
#15
0#
#16
1#
b0000000000000000000000000000000000000000000000000000000000000011 &
b0000000000000000000000000000000000000000000000000000000000000101 (
b0000000000000000000000000000000000000000000000000000000000000011 *
#17
0#
#18
1#
b0000000000000000000000000000000000000000000000000000000000000101 &
b0000000000000000000000000000000000000000000000000000000000001000 (
b0000000000000000000000000000000000000000000000000000000000000101 *
#19
0#
#20
1#
b0000000000000000000000000000000000000000000000000000000000001000 &
b0000000000000000000000000000000000000000000000000000000000001101 (
b0000000000000000000000000000000000000000000000000000000000001000 *
#21
0#
#22
1#
b0000000000000000000000000000000000000000000000000000000000001101 &
b0000000000000000000000000000000000000000000000000000000000010101 (
b0000000000000000000000000000000000000000000000000000000000001101 *
#23
0#
#24
1#
b0000000000000000000000000000000000000000000000000000000000010101 &
b0000000000000000000000000000000000000000000000000000000000100010 (
b0000000000000000000000000000000000000000000000000000000000010101 *
#25
0#
#26
1#
b0000000000000000000000000000000000000000000000000000000000100010 &
b0000000000000000000000000000000000000000000000000000000000110111 (
b0000000000000000000000000000000000000000000000000000000000100010 *
#27
0#
#28
1#
b0000000000000000000000000000000000000000000000000000000000110111 &
b0000000000000000000000000000000000000000000000000000000001011001 (
b0000000000000000000000000000000000000000000000000000000000110111 *
#29
0#
#30
1#
b0000000000000000000000000000000000000000000000000000000001011001 &
b0000000000000000000000000000000000000000000000000000000010010000 (
b0000000000000000000000000000000000000000000000000000000001011001 *
#31
0#
#32
1#
b0000000000000000000000000000000000000000000000000000000010010000 &
b0000000000000000000000000000000000000000000000000000000011101001 (
b0000000000000000000000000000000000000000000000000000000010010000 *
#33
0#
#34
1#
b0000000000000000000000000000000000000000000000000000000011101001 &
b0000000000000000000000000000000000000000000000000000000101111001 (
b0000000000000000000000000000000000000000000000000000000011101001 *
#35
0#
#36
1#
b0000000000000000000000000000000000000000000000000000000101111001 &
b0000000000000000000000000000000000000000000000000000001001100010 (
b0000000000000000000000000000000000000000000000000000000101111001 *
#37
0#
#38
1#
b0000000000000000000000000000000000000000000000000000001001100010 &
b0000000000000000000000000000000000000000000000000000001111011011 (
b0000000000000000000000000000000000000000000000000000001001100010 *
#39
0#
#40
1#
b0000000000000000000000000000000000000000000000000000001111011011 &
b0000000000000000000000000000000000000000000000000000011000111101 (
b0000000000000000000000000000000000000000000000000000001111011011 *
#41
0#
#42
1#
b0000000000000000000000000000000000000000000000000000011000111101 &
b0000000000000000000000000000000000000000000000000000101000011000 (
b0000000000000000000000000000000000000000000000000000011000111101 *
#43
0#
#44
1#
b0000000000000000000000000000000000000000000000000000101000011000 &
b0000000000000000000000000000000000000000000000000001000001010101 (
b0000000000000000000000000000000000000000000000000000101000011000 *
#45
0#
#46
1#
b0000000000000000000000000000000000000000000000000001000001010101 &
b0000000000000000000000000000000000000000000000000001101001101101 (
b0000000000000000000000000000000000000000000000000001000001010101 *
#47
0#
#48
1#
b0000000000000000000000000000000000000000000000000001101001101101 &
b0000000000000000000000000000000000000000000000000010101011000010 (
b0000000000000000000000000000000000000000000000000001101001101101 *
#49
0#
#50
1#
b0000000000000000000000000000000000000000000000000010101011000010 &
b0000000000000000000000000000000000000000000000000100010100101111 (
b0000000000000000000000000000000000000000000000000010101011000010 *
#51
0#
#52
1#
b0000000000000000000000000000000000000000000000000100010100101111 &
b0000000000000000000000000000000000000000000000000110111111110001 (
b0000000000000000000000000000000000000000000000000100010100101111 *
#53
0#
#54
1#
b0000000000000000000000000000000000000000000000000110111111110001 &
b0000000000000000000000000000000000000000000000001011010100100000 (
b0000000000000000000000000000000000000000000000000110111111110001 *
#55
0#
#56
1#
b0000000000000000000000000000000000000000000000001011010100100000 &
b0000000000000000000000000000000000000000000000010010010100010001 (
b0000000000000000000000000000000000000000000000001011010100100000 *
#57
0#
#58
1#
b0000000000000000000000000000000000000000000000010010010100010001 &
b0000000000000000000000000000000000000000000000011101101000110001 (
b0000000000000000000000000000000000000000000000010010010100010001 *
#59
0#
#60
1#
b0000000000000000000000000000000000000000000000011101101000110001 &
b0000000000000000000000000000000000000000000000101111111101000010 (
b0000000000000000000000000000000000000000000000011101101000110001 *
#61
0#
#62
1#
b0000000000000000000000000000000000000000000000101111111101000010 &
b0000000000000000000000000000000000000000000001001101100101110011 (
b0000000000000000000000000000000000000000000000101111111101000010 *
#63
0#
#64
1#
b0000000000000000000000000000000000000000000001001101100101110011 &
b0000000000000000000000000000000000000000000001111101100010110101 (
b0000000000000000000000000000000000000000000001001101100101110011 *
#65
0#
#66
1#
b0000000000000000000000000000000000000000000001111101100010110101 &
b0000000000000000000000000000000000000000000011001011001000101000 (
b0000000000000000000000000000000000000000000001111101100010110101 *
#67
0#
#68
1#
b0000000000000000000000000000000000000000000011001011001000101000 &
b0000000000000000000000000000000000000000000101001000101011011101 (
b0000000000000000000000000000000000000000000011001011001000101000 *
#69
0#
#70
1#
b0000000000000000000000000000000000000000000101001000101011011101 &
b0000000000000000000000000000000000000000001000010011110100000101 (
b0000000000000000000000000000000000000000000101001000101011011101 *
#71
0#
#72
1#
b0000000000000000000000000000000000000000001000010011110100000101 &
b0000000000000000000000000000000000000000001101011100011111100010 (
b0000000000000000000000000000000000000000001000010011110100000101 *
#73
0#
#74
1#
b0000000000000000000000000000000000000000001101011100011111100010 &
b0000000000000000000000000000000000000000010101110000010011100111 (
b0000000000000000000000000000000000000000001101011100011111100010 *
#75
0#
#76
1#
b0000000000000000000000000000000000000000010101110000010011100111 &
b0000000000000000000000000000000000000000100011001100110011001001 (
b0000000000000000000000000000000000000000010101110000010011100111 *
#77
0#
#78
1#
b0000000000000000000000000000000000000000100011001100110011001001 &
b0000000000000000000000000000000000000000111000111101000110110000 (
b0000000000000000000000000000000000000000100011001100110011001001 *
#79
0#
#80
1#
b0000000000000000000000000000000000000000111000111101000110110000 &
b0000000000000000000000000000000000000001011100001001111001111001 (
b0000000000000000000000000000000000000000111000111101000110110000 *
#81
0#
#82
1#
b0000000000000000000000000000000000000001011100001001111001111001 &
b0000000000000000000000000000000000000010010101000111000000101001 (
b0000000000000000000000000000000000000001011100001001111001111001 *
#83
0#
#84
1#
b0000000000000000000000000000000000000010010101000111000000101001 &
b0000000000000000000000000000000000000011110001010000111010100010 (
b0000000000000000000000000000000000000010010101000111000000101001 *
#85
0#
#86
1#
b0000000000000000000000000000000000000011110001010000111010100010 &
b0000000000000000000000000000000000000110000110010111111011001011 (
b0000000000000000000000000000000000000011110001010000111010100010 *
#87
0#
#88
1#
b0000000000000000000000000000000000000110000110010111111011001011 &
b0000000000000000000000000000000000001001110111101000110101101101 (
b0000000000000000000000000000000000000110000110010111111011001011 *
#89
0#
#90
1#
b0000000000000000000000000000000000001001110111101000110101101101 &
b0000000000000000000000000000000000001111111110000000110000111000 (
b0000000000000000000000000000000000001001110111101000110101101101 *
#91
0#
#92
1#
b0000000000000000000000000000000000001111111110000000110000111000 &
b0000000000000000000000000000000000011001110101101001100110100101 (
b0000000000000000000000000000000000001111111110000000110000111000 *
#93
0#
#94
1#
b0000000000000000000000000000000000011001110101101001100110100101 &
b0000000000000000000000000000000000101001110011101010010111011101 (
b0000000000000000000000000000000000011001110101101001100110100101 *
#95
0#
#96
1#
b0000000000000000000000000000000000101001110011101010010111011101 &
b0000000000000000000000000000000001000011101001010011111110000010 (
b0000000000000000000000000000000000101001110011101010010111011101 *
#97
0#
#98
1#
b0000000000000000000000000000000001000011101001010011111110000010 &
b0000000000000000000000000000000001101101011100111110010101011111 (
b0000000000000000000000000000000001000011101001010011111110000010 *
